CtqKit/__init__.py
CtqKit/account.py
CtqKit/circuit/__init__.py
CtqKit/circuit/barrier.py
CtqKit/circuit/gate/__init__.py
CtqKit/circuit/gate/gate.py
CtqKit/circuit/gate/h.py
CtqKit/circuit/gate/i.py
CtqKit/circuit/gate/rx.py
CtqKit/circuit/gate/rxy.py
CtqKit/circuit/gate/ry.py
CtqKit/circuit/gate/rz.py
CtqKit/circuit/gate/s.py
CtqKit/circuit/gate/t.py
CtqKit/circuit/gate/x.py
CtqKit/circuit/gate/x2m.py
CtqKit/circuit/gate/x2p.py
CtqKit/circuit/gate/y.py
CtqKit/circuit/gate/y2m.py
CtqKit/circuit/gate/y2p.py
CtqKit/circuit/gate/z.py
CtqKit/circuit/instruction.py
CtqKit/circuit/measure.py
CtqKit/platform.py
ctqkit-0.1.8.dist-info/LICENSE.txt
ctqkit-0.1.8.dist-info/METADATA
ctqkit-0.1.8.dist-info/WHEEL
ctqkit-0.1.8.dist-info/RECORD
