Metadata-Version: 2.1
Name: CtqKit
Version: 0.1.8
Summary: 中国电信天衍量子计算云平台 Python SDK (ChinaTelecom Quantum Kit)
Home-page: https://qc.zdxlz.com/
License: Apache 2.0
Author: Gao Jianjian
Author-email: jianjian001@outlook.com
Requires-Python: >=3.8,<4.0
Classifier: License :: OSI Approved :: Apache Software License
Classifier: License :: Other/Proprietary License
Classifier: Operating System :: OS Independent
Classifier: Programming Language :: Python :: 3
Classifier: Programming Language :: Python :: 3.8
Classifier: Programming Language :: Python :: 3.9
Classifier: Programming Language :: Python :: 3.10
Classifier: Programming Language :: Python :: 3.11
Classifier: Topic :: Software Development :: Libraries
Requires-Dist: numpy (>=1.24.0,<2.0.0)
Requires-Dist: requests (>=2.31.0,<3.0.0)
Project-URL: Documentation, https://qc.zdxlz.com/informationSpace
